README
setup.py
goral/__init__.py
goral/timeutils.py
goral.egg-info/PKG-INFO
goral.egg-info/SOURCES.txt
goral.egg-info/dependency_links.txt
goral.egg-info/requires.txt
goral.egg-info/top_level.txt