Metadata-Version: 1.1
Name: goral
Version: 0.0.0
Summary: A utility for China Stock
Home-page: https://github.com/caviler/goral
Author: caviler
Author-email: caviler@gmail.com
License: BSD
Keywords: goral finance trade quant
Platform: UNKNOWN
Classifier: Development Status :: 3 - Alpha
Classifier: Programming Language :: Python :: 2.7
Classifier: Programming Language :: Python :: 3.4
Classifier: Programming Language :: Python :: 3.5
Classifier: License :: OSI Approved :: BSD License
